Verilog/ASSIGNMENTS/assignment7/04.Testbench/58.Update reg.v/register4.v
module register4(
input clk,
input [3:0] d,
output reg [3:0] q
);

	always @(posedge clk) begin
	     q <= d;
	end
endmodule

Verilog/ASSIGNMENTS/assignment7/04.Testbench/58.Update reg.v/tb_register4.v
module tb_register4;
reg clk;
reg [3:0] d;
wire [3:0] q;

register4 uut(.clk(clk),.d(d),.q(q));

	initial begin
	clk=0;
	end 

	always #5 clk=~clk;


	initial begin
	$dumpfile("register4.vcd");
	$dumpvars(0,tb_register4);

	$display("time | clk | d | q");
	$monitor("time=%0t,clk=%b,d=%b,q=%b",$time,clk,d,q);

	d=4'b1010;#10;
	d=4'b1111;#10;
	d=4'b1100;#10;
	d=4'b0000;#10;
	d=4'b1001;#10;
	$finish;
	end
endmodule

Verilog/ASSIGNMENTS/assignment7/04.Testbench/58.Update reg.v/register4.vcd
$date
	Sat Sep 20 05:49:06 2025
$end
$version
	Icarus Verilog
$end
$timescale
	1s
$end
$scope module tb_register4 $end
$var wire 4 ! q [3:0] $end
$var reg 1 " clk $end
$var reg 4 # d [3:0] $end
$scope module uut $end
$var wire 1 " clk $end
$var wire 4 $ d [3:0] $end
$var reg 4 % q [3:0] $end
$upscope $end
$upscope $end
$enddefinitions $end
$comment Show the parameter values. $end
$dumpall
$end
#0
$dumpvars
bx %
b1010 $
b1010 #
0"
bx !
$end
#5
b1010 !
b1010 %
1"
#10
0"
b1111 #
b1111 $
#15
b1111 !
b1111 %
1"
#20
0"
b1100 #
b1100 $
#25
b1100 !
b1100 %
1"
#30
0"
b0 #
b0 $
#35
b0 !
b0 %
1"
#40
0"
b1001 #
b1001 $
#45
b1001 !
b1001 %
1"
