Verilog/ASSIGNMENTS/assignment8/qns.09/even_odd.v
module even_odd(
input clk,
input rst,
input in,
output reg odd0,odd1,even0,even1
);

parameter s0 = 0;
parameter s1 = 1;
parameter s2 = 2;
parameter s3 = 3;

reg [1:0] state , next_state;

always @(in or state) begin
	case(state)
	s0:begin
		if(in)
			next_state = s1;
		else
			next_state = s2;
	end
	s1:begin
		if(in)
			next_state = s0;
		else
			next_state = s3;
	end
	s2:begin
		if(in)
			next_state = s3;
		else 
			next_state = s0;
	end
	s3:begin
		if(in)
			next_state = s2;
		else 
			next_state = s1;
	end
	default: next_state = s0;
	endcase
end

always @(state) begin
	case(state)
		s0:begin
			even0=1;even1=1;odd0=0;odd1=0;
		end
		s1:begin
			even0=1;even1=0;odd0=0;odd1=1;
		end
		s2:begin
			even0=0;even1=1;odd0=1;odd1=0;
		end
		s3:begin
			even0=0;even1=0;odd0=1;odd1=1;
		end
		default: begin
			even0=1;even1=1;odd0=0;odd1=0;
		end

	endcase
end

always @(posedge clk or posedge rst) begin
	if(rst)
		state <= s0;
	else
		state <= next_state;
end

endmodule

Verilog/ASSIGNMENTS/assignment8/qns.09/tb_even_odd.v
module tb_even_odd;
reg clk,rst,in;
wire odd0,odd1,even0,even1;

even_odd uut(.clk(clk),.rst(rst),.in(in),.odd0(odd0),.odd1(odd1),.even0(even0),.even1(even1));

always #5 clk =~clk;

initial begin
		$dumpfile("even_odd.vcd");
		$dumpvars;
		$monitor("time=%0t rst=%b | clk=%b| in=%b | even0=%b | even1=%b | odd0=%b | odd1=%b",$time,rst,clk,in,even0,even1,odd0,odd1);
	        clk=0;		
		rst = 1;
		in = 0;
		#10;
		rst = 0;
		in = 1;
		#10 in = 0;
		#10 in = 1;
		#10 in = 1;
		#10 in = 0;
		#10 in = 0;
		#10 in = 1;

		#20 $finish;
		
	end
endmodule

Verilog/ASSIGNMENTS/assignment8/qns.09/even_odd.vcd
$date
	Fri Oct 31 12:14:06 2025
$end
$version
	Icarus Verilog
$end
$timescale
	1s
$end
$scope module tb_even_odd $end
$var wire 1 ! odd1 $end
$var wire 1 " odd0 $end
$var wire 1 # even1 $end
$var wire 1 $ even0 $end
$var reg 1 % clk $end
$var reg 1 & in $end
$var reg 1 ' rst $end
$scope module uut $end
$var wire 1 % clk $end
$var wire 1 & in $end
$var wire 1 ' rst $end
$var parameter 32 ( s0 $end
$var parameter 32 ) s1 $end
$var parameter 32 * s2 $end
$var parameter 32 + s3 $end
$var reg 1 $ even0 $end
$var reg 1 # even1 $end
$var reg 2 , next_state [1:0] $end
$var reg 1 " odd0 $end
$var reg 1 ! odd1 $end
$var reg 2 - state [1:0] $end
$upscope $end
$upscope $end
$enddefinitions $end
$comment Show the parameter values. $end
$dumpall
b11 +
b10 *
b1 )
b0 (
$end
#0
$dumpvars
b0 -
b10 ,
1'
0&
0%
1$
1#
0"
0!
$end
#5
1%
#10
b1 ,
0%
1&
0'
#15
1!
0#
b0 ,
b1 -
1%
#20
b11 ,
0%
0&
#25
1"
0$
b1 ,
b11 -
1%
#30
b10 ,
0%
1&
#35
0!
1#
b11 ,
b10 -
1%
#40
0%
#45
1!
0#
b10 ,
b11 -
1%
#50
b1 ,
0%
0&
#55
0"
1$
b11 ,
b1 -
1%
#60
0%
#65
1"
0$
b1 ,
b11 -
1%
#70
b10 ,
0%
1&
#75
0!
1#
b11 ,
b10 -
1%
#80
0%
#85
1!
0#
b10 ,
b11 -
1%
