Verilog/ASSIGNMENTS/assignment8/qns.06/two_one.v
module two_one(
input clk,
input rst,
input in,
output reg out
);

parameter s0 = 3'b000;
parameter s1 = 3'b001;
parameter s2 = 3'b010;
parameter s3 = 3'b011;
parameter s4 = 3'b100;
parameter s5 = 3'b101;
parameter s6 = 3'b110;
parameter s7 = 3'b111;

reg [2:0] state,next_state;
always @ (in or state)
begin
	case(state)
		s0:begin
			if(in)begin
				next_state = s1;
			end
			else begin
				next_state = s0;
			end
			out = 0;
		end

		s1:begin
			if(in)begin
                                next_state = s3;
			end
			else begin
                                next_state = s2;
			end
                        out = 0;
                end

		s2:begin
			if(in) begin
                                next_state = s5;
			end
			else begin
                                next_state = s4;
			end
                        out = 0;
                end

		s3:begin
                        if(in)begin
                                next_state = s7;
			end
			else begin
                                next_state = s6;
			end
                        out = 1;
                end

		s4:begin
			if(in) begin
                                next_state = s1;
			end
			else begin
                                next_state = s0;
			end
                        out = 0;
                end

		s5:begin
			if(in) begin
                                next_state = s3;
			end
			else begin
                                next_state = s2;
			end
                        out = 1;
                end

		s6:begin
			if(in)begin
                                next_state = s5;
		           end
			   else begin
                                next_state = s4;
			end
                        out = 1;
                end

		s7:begin
			if(in) begin
                                next_state = s7;
			end
			else begin
                                next_state = s6;
			end
                        out = 1;
                end

		default: next_state = s0;
	endcase
end

always @(posedge clk or posedge rst) begin
	if(rst)
		state <= s0;
	else 
		state <= next_state;
end

endmodule

Verilog/ASSIGNMENTS/assignment8/qns.06/tb_two_one.v
module tb_two_one;
reg clk,rst,in;
wire out;
always #5 clk=~clk;
two_one uut (.clk(clk), .rst(rst), .in(in), .out(out));
initial begin
	$dumpfile("sec.vcd");
	$dumpvars(0);
	$monitor(" Time= %t  |state =%b |in=%b| next_state =%b| out= %b",$time,uut.state, in,uut.next_state,out);
        clk=0;

	rst=1;#5;
	rst=0;

	in=0;#10;
	in=1;#10;
	in=0;#10;
	in=0;#10;
	in=1;#10;
	in=0;#10;
	in=0;#10;
	in=1;#10;
	in=0;#10;
	in=1;#10;
	in=1;#10;
	in=0;#10;
	in=0;#10;
	in=1;#10;
	in=1;#10;
	in=0;#10;
	in=0;#10;
	in=1;#10;
	$finish;
end
endmodule

Verilog/ASSIGNMENTS/assignment8/qns6/sec.vcd
$date
	Fri Oct 31 04:54:50 2025
$end
$version
	Icarus Verilog
$end
$timescale
	1s
$end
$scope module tb_two_one $end
$var wire 1 ! out $end
$var reg 1 " clk $end
$var reg 1 # in $end
$var reg 1 $ rst $end
$scope module uut $end
$var wire 1 " clk $end
$var wire 1 # in $end
$var wire 1 $ rst $end
$var parameter 3 % s0 $end
$var parameter 3 & s1 $end
$var parameter 3 ' s2 $end
$var parameter 3 ( s3 $end
$var parameter 3 ) s4 $end
$var parameter 3 * s5 $end
$var parameter 3 + s6 $end
$var parameter 3 , s7 $end
$var reg 3 - next_state [2:0] $end
$var reg 1 ! out $end
$var reg 3 . state [2:0] $end
$upscope $end
$upscope $end
$enddefinitions $end
$comment Show the parameter values. $end
$dumpall
b111 ,
b110 +
b101 *
b100 )
b11 (
b10 '
b1 &
b0 %
$end
#0
$dumpvars
b0 .
b0 -
1$
x#
0"
0!
$end
#5
0#
0$
1"
#10
0"
#15
b1 .
b11 -
1"
1#
#20
0"
#25
b10 .
b100 -
1"
0#
#30
0"
#35
b0 -
b100 .
1"
#40
0"
#45
b1 .
b11 -
1"
1#
#50
0"
#55
b10 .
b100 -
1"
0#
#60
0"
#65
b0 -
b100 .
1"
#70
0"
#75
b1 .
b11 -
1"
1#
#80
0"
#85
b10 .
b100 -
1"
0#
#90
0"
#95
1!
b101 .
b11 -
1"
1#
#100
0"
#105
b111 -
b11 .
1"
#110
0"
#115
b110 .
b100 -
1"
0#
#120
0"
#125
0!
b0 -
b100 .
1"
#130
0"
#135
b1 .
b11 -
1"
1#
#140
0"
#145
1!
b111 -
b11 .
1"
#150
0"
#155
b110 .
b100 -
1"
0#
#160
0"
#165
0!
b0 -
b100 .
1"
#170
0"
#175
b1 .
b11 -
1"
1#
#180
0"
#185
1!
b111 -
b11 .
1"
