Verilog/ASSIGNMENTS/assignment8/qns11/state2_in2.v
module state2_in2(
input clk,
input rst,
input j,k,
output reg out
);

parameter OFF = 0;
parameter ON = 1;

reg [1:0] state , next_state;

always @(*) begin
	case(state)
		OFF:begin
			if (j==1) begin next_state = ON; end
			else begin next_state = OFF; end
			out = 0;
		end
		ON:begin
			if (k==1) begin next_state = OFF; end
			else begin next_state = ON; end
			out = 1;
		end
		default: next_state = OFF;
	endcase
end

always @(posedge clk or posedge rst) begin
	if(rst)
		state <= 0;
	else 
		state <= next_state;
end

endmodule

Verilog/ASSIGNMENTS/assignment8/qns.11/tb_state2_in2.v
module tb_state2_in2;
reg clk,rst,j,k;
wire out;

state2_in2 uut(.clk(clk),.rst(rst),.j(j),.k(k),.out(out));

always #5 clk =~clk;

                initial begin
        	$dumpfile("sec.vcd");
		$dumpvars(0);
		$monitor("Time=%0t | j=%b k=%b | out=%b", $time, j, k, out);
  		
		clk = 0;
		rst = 1;
    		j = 0;
   		k = 0;
		#10 rst = 0;
		#10 j = 1;
  		#10 j = 0;
		#20;
		
		k = 1;
		#10 k = 0;
		#10 j = 1; #10 j = 0;
    		#10 k = 1; #10 k = 0;
		#20 $finish;
	        
	        end

endmodule

Verilog/ASSIGNMENTS/assignment8/qns11/sec.vcd
$date
	Fri Oct 31 08:47:51 2025
$end
$version
	Icarus Verilog
$end
$timescale
	1s
$end
$scope module tb_state2_in2 $end
$var wire 1 ! out $end
$var reg 1 " clk $end
$var reg 1 # j $end
$var reg 1 $ k $end
$var reg 1 % rst $end
$scope module uut $end
$var wire 1 " clk $end
$var wire 1 # j $end
$var wire 1 $ k $end
$var wire 1 % rst $end
$var parameter 32 & OFF $end
$var parameter 32 ' ON $end
$var reg 2 ( next_state [1:0] $end
$var reg 1 ! out $end
$var reg 2 ) state [1:0] $end
$upscope $end
$upscope $end
$enddefinitions $end
$comment Show the parameter values. $end
$dumpall
b1 '
b0 &
$end
#0
$dumpvars
b0 )
b0 (
1%
0$
0#
0"
0!
$end
#5
1"
#10
0"
0%
#15
1"
#20
b1 (
0"
1#
#25
1!
b1 )
1"
#30
0"
0#
#35
1"
#40
0"
#45
1"
#50
b0 (
0"
1$
#55
0!
b0 )
1"
#60
0"
0$
#65
1"
#70
b1 (
0"
1#
#75
1!
b1 )
1"
#80
0"
0#
#85
1"
#90
b0 (
0"
1$
#95
0!
b0 )
1"
#100
0"
0$
