Verilog/ASSIGNMENTS/assignment7/04.Testbench/59.Regfile.v/regfile4x4.v
module regfile4x4(
input clk,
input we,
input [1:0] waddr,raddr,
input [3:0] wdata,
output [3:0] rdata
);

	reg[3:0] regs[3:0];

	always @(posedge clk) begin
	    if(we)
		regs[waddr] <= wdata;
	end

	assign rdata = regs[raddr];
endmodule

Verilog/ASSIGNMENTS/assignment7/04.Testbench/59.Regfile.v/tb_regfile4x4.v
module tb_regfile4x4;
    reg clk;
    reg we;
    reg [1:0] waddr, raddr;
    reg [3:0] wdata;
    wire [3:0] rdata;
    integer i;

  
    regfile4x4 uut (
        .clk(clk),
        .we(we),
        .waddr(waddr),
        .raddr(raddr),
        .wdata(wdata),
        .rdata(rdata)
    );

   
    initial clk = 0;
    always #5 clk = ~clk;

    initial begin
        $dumpfile("regfile4x4.vcd");
        $dumpvars(0, tb_regfile4x4);

        $display("WRITE PHASE:");
        $display("Time\tWE WAddr WData");
        
   
        we = 1;
        for (i = 0; i < 4; i = i + 1) begin
            waddr = i;
            wdata = i + 1; // example data
            #10;
            $display("%0t\t %b   %b    %b", $time, we, waddr, wdata);
        end

        we = 0;

        $display("\nREAD PHASE:");
        $display("Time\tRAddr RData");
        for (i = 0; i < 4; i = i + 1) begin
            raddr = i;
            #10;
            $display("%0t\t %b    %b", $time, raddr, rdata);
        end

        $finish;
    end
endmodule

Verilog/ASSIGNMENTS/assignment7/04.Testbench/59.Regfile.v/regfile4x4.vcd
$date
	Sat Sep 20 06:23:28 2025
$end
$version
	Icarus Verilog
$end
$timescale
	1s
$end
$scope module tb_regfile4x4 $end
$var wire 4 ! rdata [3:0] $end
$var reg 1 " clk $end
$var reg 2 # raddr [1:0] $end
$var reg 2 $ waddr [1:0] $end
$var reg 4 % wdata [3:0] $end
$var reg 1 & we $end
$var integer 32 ' i [31:0] $end
$scope module uut $end
$var wire 1 " clk $end
$var wire 2 ( raddr [1:0] $end
$var wire 4 ) rdata [3:0] $end
$var wire 2 * waddr [1:0] $end
$var wire 4 + wdata [3:0] $end
$var wire 1 & we $end
$upscope $end
$upscope $end
$enddefinitions $end
$comment Show the parameter values. $end
$dumpall
$end
#0
$dumpvars
b1 +
b0 *
bx )
bx (
b0 '
1&
b1 %
b0 $
bx #
0"
bx !
$end
#5
1"
#10
0"
b10 %
b10 +
b1 $
b1 *
b1 '
#15
1"
#20
0"
b11 %
b11 +
b10 $
b10 *
b10 '
#25
1"
#30
0"
b100 %
b100 +
b11 $
b11 *
b11 '
#35
1"
#40
0"
b1 !
b1 )
b0 #
b0 (
0&
b0 '
#45
1"
#50
0"
b10 !
b10 )
b1 #
b1 (
b1 '
#55
1"
#60
0"
b11 !
b11 )
b10 #
b10 (
b10 '
#65
1"
#70
0"
b100 !
b100 )
b11 #
b11 (
b11 '
#75
1"
#80
0"
b100 '
