Verilog/ASSIGNMENTS/assignment7/04.Testbench/52.Dff_async.v/dff_async.v
module dff_async(
input clk,rst,d,
output reg q
);

	always @(posedge clk or posedge rst) begin
	   if(rst)
		q <= 0;
	   else
		q <= d;
	end
endmodule

Verilog/ASSIGNMENTS/assignment7/04.Testbench/52.Dff_async.v/tb_dff_async.v
module tb_dff_async;
reg clk,rst,d;
wire q;

dff_async uut(.clk(clk),.rst(rst),.d(d),.q(q));

	initial begin
		clk=0;
	forever #5 clk=~clk;
	end

	initial begin
	$dumpfile("dff_async.vcd");
	$dumpvars(0,tb_dff_async);

	$display("time|tclk|trst|td|tq");
	$monitor("%0t|%b|%b|%b|%b",$time,clk,rst,d,q);

	rst = 1; d = 0; #12;
        rst = 0; d = 1; #10;  
        d = 0; #10;       
        d = 1; #10;            
        rst = 1; #7;        
        rst = 0; d = 0; #10;   
        d = 1; #10;

	$finish;
	end
endmodule

Verilog/ASSIGNMENTS/assignment7/04.Testbench/52.Dff_async.v/dff_async.vcd
$date
	Sat Sep 20 04:22:42 2025
$end
$version
	Icarus Verilog
$end
$timescale
	1s
$end
$scope module tb_dff_async $end
$var wire 1 ! q $end
$var reg 1 " clk $end
$var reg 1 # d $end
$var reg 1 $ rst $end
$scope module uut $end
$var wire 1 " clk $end
$var wire 1 # d $end
$var wire 1 $ rst $end
$var reg 1 ! q $end
$upscope $end
$upscope $end
$enddefinitions $end
$comment Show the parameter values. $end
$dumpall
$end
#0
$dumpvars
1$
0#
0"
0!
$end
#5
1"
#10
0"
#12
1#
0$
#15
1!
1"
#20
0"
#22
0#
#25
0!
1"
#30
0"
#32
1#
#35
1!
1"
#40
0"
#42
0!
1$
#45
1"
#49
0#
0$
#50
0"
#55
1"
#59
1#
#60
0"
#65
1!
1"
