Verilog/ASSIGNMENTS/assignment5/prod_qns_11/dff_blocking.v
module dff_blocking(
input clk,
input d,
output reg q
);

always @(posedge clk) begin
	q=d;
end
endmodule

Verilog/ASSIGNMENTS/assignment5/prod_qns_11/tb_dff_blocking.v
module tb_dff_blocking;
reg clk,d;
wire q;

dff_blocking uut(.clk(clk), .d(d), .q(q));

	initial begin
	clk=0;
	forever #5 clk= ~clk;
        end

	initial begin
        $dumpfile("dff_blocking.vcd"); 
        $dumpvars(0, tb_dff_blocking);
 

	$monitor("time=%4t,clk=%b,d=%b,q=%b",$time,clk,d,q);
	
	d=0; #7;
	d=1; #10;
	d=0; #10;
	d=1; #10;
	#10 $finish;
	end
endmodule

Verilog/ASSIGNMENTS/assignment5/prod_qns_11/dff_blocking.vcd
$date
	Wed Sep 10 12:50:49 2025
$end
$version
	Icarus Verilog
$end
$timescale
	1s
$end
$scope module tb_dff_blocking $end
$var wire 1 ! q $end
$var reg 1 " clk $end
$var reg 1 # d $end
$scope module uut $end
$var wire 1 " clk $end
$var wire 1 # d $end
$var reg 1 ! q $end
$upscope $end
$upscope $end
$enddefinitions $end
$comment Show the parameter values. $end
$dumpall
$end
#0
$dumpvars
0#
0"
x!
$end
#5
0!
1"
#7
1#
#10
0"
#15
1!
1"
#17
0#
#20
0"
#25
0!
1"
#27
1#
#30
0"
#35
1!
1"
