Verilog/ASSIGNMENTS/assignment5/condition_qns_43/priority_base_if.v
module priority_based_if(
input in1,in2,in3 ,
output reg [1:0] out
);

	always @(*) begin
	   if(in1==1)
		out=2'b11;
	   else if(in2==1)
		out=2'b10;
	   else if(in3==1)
		out=2'b01;
	   else
	     	out=2'b00;
	end
endmodule

Verilog/ASSIGNMENTS/assignment5/condition_qns_43/tb_priority_base_if.v
module tb_priority_base_if;
reg in1,in2,in3;
wire [1:0] out;

 priority_based_if uut(.in1(in1),.in2(in2),.in3(in3),.out(out));

	initial begin
	$dumpfile("tb_priority_base_if.vcd");
	$dumpvars(0,tb_priority_base_if);

	$display("time | in1 in2 in3 | out");
	$monitor("%4t | %b %b %b | %b",$time,in1,in2,in3,out);

	in1=1; in2=0; in3=0;#10;
	in1=0; in2=1; in3=0;#10;
	in1=0; in2=0; in3=1;#10;
	in1=1; in2=1; in3=0;#10;
	in1=0; in2=1; in3=1;#10;
	in1=1; in2=0; in3=1;#10;
	in1=1; in2=1; in3=1;#10;
	in1=0; in2=0; in3=0;#10;
	$finish;
	end
endmodule

Verilog/ASSIGNMENTS/assignment5/condition_qns_43/tb_priority_base_if.vcd
$date
	Fri Sep 12 06:42:01 2025
$end
$version
	Icarus Verilog
$end
$timescale
	1s
$end
$scope module tb_priority_base_if $end
$var wire 2 ! out [1:0] $end
$var reg 1 " in1 $end
$var reg 1 # in2 $end
$var reg 1 $ in3 $end
$scope module uut $end
$var wire 1 " in1 $end
$var wire 1 # in2 $end
$var wire 1 $ in3 $end
$var reg 2 % out [1:0] $end
$upscope $end
$upscope $end
$enddefinitions $end
$comment Show the parameter values. $end
$dumpall
$end
#0
$dumpvars
b11 %
0$
0#
1"
b11 !
$end
#10
b10 !
b10 %
1#
0"
#20
b1 !
b1 %
1$
0#
#30
b11 !
b11 %
0$
1#
1"
#40
b10 !
b10 %
1$
0"
#50
b11 !
b11 %
0#
1"
#60
1#
#70
b0 !
b0 %
0$
0#
0"
