Verilog/day2/dataflow/ripplecarry/ripplecarry.v
module ripplecarry(a,b,cin,sum,cout);
input[3:0] a,b;
input cin;
output[3:0] sum;
output cout;
wire c1,c2,c3;


assign {c1,sum[0]} = a[0] + b[0] + cin;
assign {c2,sum[1]} = a[1] + b[1] + c1;
assign {c3,sum[2]} = a[2] + b[2] + c2;
assign {cout,sum[3]} = a[3] + b[3] + c3;

endmodule

Verilog/day2/dataflow/ripplecarry/tb_ripplecarry.v
module tb_ripplecarry;
	reg [3:0] a, b;
	reg cin;
	wire [3:0] sum;
	wire cout;

	ripplecarry uut(.a(a), .b(b), .cin(cin), .sum(sum), .cout(cout));

	initial begin
	       $dumpfile("ripplecarry_wave.vcd");
	       $dumpvars(0, tb_ripplecarry);

	       $display(" a    b   cin | sum  cout");
	       $monitor("%b %b  %b  | %b   %b", a, b, cin, sum, cout);

	       a=4'b1010; b=4'b1001; cin=0; #10;
	       a=4'b1001; b=4'b1101; cin=1; #10;
	       a=4'b1010; b=4'b1111; cin=0; #10;
	       a=4'b1001; b=4'b0011; cin=1; #10;
	       a=4'b0110; b=4'b1001; cin=1; #10;
	       a=4'b1110; b=4'b0111; cin=0; #10;
	       a=4'b1010; b=4'b1101; cin=1; #10;
	       a=4'b1010; b=4'b1111; cin=1; #10;

	       $finish;
	       end
endmodule

Verilog/day2/dataflow/ripplecarry/ripplecarry_wave.vcd
$date
	Wed Sep 10 06:13:55 2025
$end
$version
	Icarus Verilog
$end
$timescale
	1s
$end
$scope module tb_ripplecarry $end
$var wire 4 ! sum [3:0] $end
$var wire 1 " cout $end
$var reg 4 # a [3:0] $end
$var reg 4 $ b [3:0] $end
$var reg 1 % cin $end
$scope module uut $end
$var wire 4 & a [3:0] $end
$var wire 4 ' b [3:0] $end
$var wire 1 % cin $end
$var wire 4 ( sum [3:0] $end
$var wire 1 " cout $end
$var wire 1 ) c3 $end
$var wire 1 * c2 $end
$var wire 1 + c1 $end
$upscope $end
$upscope $end
$enddefinitions $end
$comment Show the parameter values. $end
$dumpall
$end
#0
$dumpvars
0+
0*
0)
b11 (
b1001 '
b1010 &
0%
b1001 $
b1010 #
1"
b11 !
$end
#10
b111 !
b111 (
1+
1%
b1101 $
b1101 '
b1001 #
b1001 &
#20
b1001 !
b1001 (
1)
0+
1*
0%
b1111 $
b1111 '
b1010 #
b1010 &
#30
0"
0)
b1101 !
b1101 (
1+
1%
b11 $
b11 '
b1001 #
b1001 &
#40
1"
b0 !
b0 (
1)
b1001 $
b1001 '
b110 #
b110 &
#50
b101 !
b101 (
0+
0%
b111 $
b111 '
b1110 #
b1110 &
#60
b1000 !
b1000 (
1+
1%
b1101 $
b1101 '
b1010 #
b1010 &
#70
b1010 !
b1010 (
b1111 $
b1111 '
