Verilog/ASSIGNMENTS/assignment7/04.Testbench/53.Fulladder_testbench.v/full_adder.v
module full_adder(
input a,b,cin,
output sum,cout
);

	assign {cout,sum} = a + b + cin;
endmodule

Verilog/ASSIGNMENTS/assignment7/04.Testbench/53.Fulladder_testbench.v/tb_full_adder.v
module tb_full_adder;
reg a,b,cin;
wire cout,sum;

full_adder uut(.a(a),.b(b),.cin(cin),.sum(sum),.cout(cout));

integer i;
 	initial begin
	$dumpfile("full_adder.vcd");
	$dumpvars(0,tb_full_adder);

	$display("Time | ta b cin | sum cout");

	for(i=0;i<8;i=i+1) begin
	{a,b,cin} = i;
	#5
	$display("%0t | %b %b %b | %b %b ",$time,a,b,cin,sum,cout);
	end
	$finish;
	end
endmodule

Verilog/ASSIGNMENTS/assignment7/04.Testbench/53.Fulladder_testbench.v/full_adder.vcd
$date
	Sat Sep 20 04:44:02 2025
$end
$version
	Icarus Verilog
$end
$timescale
	1s
$end
$scope module tb_full_adder $end
$var wire 1 ! sum $end
$var wire 1 " cout $end
$var reg 1 # a $end
$var reg 1 $ b $end
$var reg 1 % cin $end
$var integer 32 & i [31:0] $end
$scope module uut $end
$var wire 1 # a $end
$var wire 1 $ b $end
$var wire 1 % cin $end
$var wire 1 ! sum $end
$var wire 1 " cout $end
$upscope $end
$upscope $end
$enddefinitions $end
$comment Show the parameter values. $end
$dumpall
$end
#0
$dumpvars
b0 &
0%
0$
0#
0"
0!
$end
#5
1!
1%
b1 &
#10
1$
0%
b10 &
#15
0!
1"
1%
b11 &
#20
1!
0"
1#
0$
0%
b100 &
#25
0!
1"
1%
b101 &
#30
1$
0%
b110 &
#35
1!
1%
b111 &
#40
b1000 &
